compresr/__init__.py
compresr/clients.py
compresr/config.py
compresr/exceptions/__init__.py
compresr/exceptions/exceptions.py
compresr/schemas/__init__.py
compresr/schemas/base.py
compresr/schemas/inference.py
compresr/schemas/usage.py
compresr/services/__init__.py
compresr/services/compression.py
compresr/services/proxy.py
compresr-1.0.16.dist-info/METADATA
compresr-1.0.16.dist-info/WHEEL
compresr-1.0.16.dist-info/top_level.txt
compresr-1.0.16.dist-info/RECORD
