Metadata-Version: 2.4
Name: compresr
Version: 1.0.16
Summary: Python SDK for Compresr - Intelligent prompt compression service
Author-email: Compresr Team <founders@compresr.ai>
License-Expression: LicenseRef-Proprietary
Project-URL: Homepage, https://compresr.com
Project-URL: Documentation, https://docs.compresr.com
Project-URL: Repository, https://github.com/compresr/sdk
Project-URL: Issues, https://github.com/compresr/sdk/issues
Keywords: llm,compression,ai,openai,gpt,tokens,cost-optimization
Classifier: Development Status :: 4 - Beta
Classifier: Intended Audience :: Developers
Classifier: Operating System :: OS Independent
Classifier: Programming Language :: Python :: 3
Classifier: Programming Language :: Python :: 3.9
Classifier: Programming Language :: Python :: 3.10
Classifier: Programming Language :: Python :: 3.11
Classifier: Programming Language :: Python :: 3.12
Classifier: Topic :: Software Development :: Libraries :: Python Modules
Classifier: Topic :: Scientific/Engineering :: Artificial Intelligence
Requires-Python: >=3.9
Requires-Dist: httpx>=0.27.0
Requires-Dist: pydantic>=2.10.0
Provides-Extra: dev
Requires-Dist: pytest>=7.0.0; extra == "dev"
Requires-Dist: pytest-asyncio>=0.21.0; extra == "dev"
Requires-Dist: pytest-cov>=4.0.0; extra == "dev"
Requires-Dist: black>=23.0.0; extra == "dev"
Requires-Dist: isort>=5.12.0; extra == "dev"
Requires-Dist: mypy>=1.0.0; extra == "dev"
